{
  "date": "2026-04-09",
  "month": 4,
  "day": 9,
  "title": "La Prueba Está en la Acción",
  "originalTitle": "The Test Is in the Doing",
  "author": "Epicteto",
  "quote": "No expliques tu filosofía. Encárnala.",
  "quoteTranslation": "Don’t explain your philosophy. Embody it.",
  "source": "Epicteto, Enquiridión, 46",
  "reflection": "Jueves. Es fácil amar las ideas nobles cuando nadie te contradice, cuando no hay presión y cuando todo marcha bien. Lo difícil —y lo importante— es demostrar esas ideas en la vida concreta.\n\nEpicteto desconfiaba de quienes hablaban mucho sobre virtud pero se quebraban ante la primera molestia. Para él, la filosofía no era decoración intelectual. Era entrenamiento para la conducta. No se trataba de sonar sabio, sino de vivir con firmeza, moderación y justicia cuando realmente costaba hacerlo.\n\nTodos tenemos cierta imagen de quienes queremos ser: pacientes, centrados, valientes, sobrios. Pero esa identidad no se confirma en el discurso sino en las pequeñas decisiones del día. Cómo respondes al mensaje que te irrita. Cómo actúas cuando nadie te ve. Cómo manejas una frustración pequeña. Ahí está la prueba.\n\nPor eso hoy conviene menos explicar y más practicar. Menos citar y más encarnar. Si valoras la templanza, demuéstrala. Si admiras la humildad, ejerce silencio. Si hablas de disciplina, cumple lo que te toca aunque no tengas ganas.\n\nLas palabras inspiran, sí. Pero solo la acción convence al alma.\n\nTu filosofía real no es la que puedes describir, sino la que puede verse en tus hábitos.",
  "tags": [
    "acción",
    "Epicteto",
    "virtud",
    "disciplina",
    "jueves",
    "abril",
    "hábitos"
  ]
}
