{
  "date": "2026-01-16",
  "month": 1,
  "day": 16,
  "title": "No Hagas que las Cosas Sean Más Difíciles de lo Necesario",
  "quote": "\"Si te angustia alguna cosa externa, el dolor no se debe a la cosa en sí, sino a tu valoración de ella; y esto tienes el poder de revocarlo en cualquier momento.\"",
  "author": "Marco Aurelio",
  "source": "Meditaciones, 8.47",
  "reflection": "Agregamos sufrimiento innecesario a nuestras vidas con nuestros juicios. Un atasco de tráfico es solo coches detenidos — somos nosotros quienes lo convertimos en una tragedia. Un correo electrónico difícil es solo palabras en una pantalla — somos nosotros quienes lo convertimos en una crisis existencial. Hoy, antes de reaccionar ante algo, pregúntate: ¿es la situación realmente terrible, o soy yo quien la está haciendo peor?",
  "tags": [
    "juicio",
    "percepción",
    "sufrimiento",
    "simplicidad"
  ]
}